symbolic_equation/__init__.py
symbolic_equation-0.3.0.dist-info/LICENSE
symbolic_equation-0.3.0.dist-info/METADATA
symbolic_equation-0.3.0.dist-info/WHEEL
symbolic_equation-0.3.0.dist-info/top_level.txt
symbolic_equation-0.3.0.dist-info/RECORD
