Metadata-Version: 2.1
Name: symbolic-equation
Version: 0.3.0
Summary: A class for multiline symbolic equations in the Jupyter Notebook
Home-page: https://github.com/goerz/symbolic_equation
Author: Michael Goerz
Author-email: mail@michaelgoerz.net
License: BSD license
Keywords: sympy,equation,algebra
Platform: UNKNOWN
Classifier: Development Status :: 3 - Alpha
Classifier: Intended Audience :: Developers
Classifier: Intended Audience :: Science/Research
Classifier: License :: OSI Approved :: BSD License
Classifier: Natural Language :: English
Classifier: Programming Language :: Python :: 3.6
Classifier: Programming Language :: Python :: 3.7
Classifier: Natural Language :: English
Classifier: Topic :: Scientific/Engineering
Requires-Python: >=3.6
Requires-Dist: uniseg
Provides-Extra: dev
Requires-Dist: black ; extra == 'dev'
Requires-Dist: coverage ; extra == 'dev'
Requires-Dist: coveralls ; extra == 'dev'
Requires-Dist: flake8 ; extra == 'dev'
Requires-Dist: gitpython ; extra == 'dev'
Requires-Dist: isort ; extra == 'dev'
Requires-Dist: ipython ; extra == 'dev'
Requires-Dist: jupyter ; extra == 'dev'
Requires-Dist: nbsphinx ; extra == 'dev'
Requires-Dist: nbval ; extra == 'dev'
Requires-Dist: pre-commit ; extra == 'dev'
Requires-Dist: pylint ; extra == 'dev'
Requires-Dist: pytest ; extra == 'dev'
Requires-Dist: pytest-cov ; extra == 'dev'
Requires-Dist: pytest-xdist ; extra == 'dev'
Requires-Dist: sympy ; extra == 'dev'
Requires-Dist: twine ; extra == 'dev'
Requires-Dist: watermark ; extra == 'dev'
Requires-Dist: wheel ; extra == 'dev'
